web_manage_mcp_server/__init__.py
web_manage_mcp_server/config.json
web_manage_mcp_server/main.py
web_manage_mcp_server/apis/__init__.py
web_manage_mcp_server/apis/java_api.py
web_manage_mcp_server/tools/__init__.py
web_manage_mcp_server/tools/java_tools.py
web_manage_mcp_server/utils/__init__.py
web_manage_mcp_server/utils/config.py
web_manage_mcp-0.4.0.dist-info/METADATA
web_manage_mcp-0.4.0.dist-info/WHEEL
web_manage_mcp-0.4.0.dist-info/entry_points.txt
web_manage_mcp-0.4.0.dist-info/RECORD
