Metadata-Version: 2.4
Name: web-manage-mcp
Version: 0.4.0
Summary: MCP server for Java backend CRUD operations with Sa-Token authentication
License: MIT
Keywords: crud,java,mcp,satoken
Requires-Python: >=3.10
Requires-Dist: asyncio-throttle>=1.0.0
Requires-Dist: httpx>=0.24.0
Requires-Dist: mcp>=1.0.0
Requires-Dist: pydantic>=2.0.0
